MANIFEST.in
__info__.py
setup.py
./appomatic_django_vcs.egg-info/SOURCES.txt
./appomatic_django_vcs.egg-info/dependency_links.txt
./appomatic_django_vcs.egg-info/requires.txt
./appomatic_django_vcs.egg-info/top_level.txt
appomatic_django_vcs/__app__.py
appomatic_django_vcs/__init__.py
appomatic_django_vcs/__urls__.py
appomatic_django_vcs.egg-info/PKG-INFO
appomatic_django_vcs.egg-info/SOURCES.txt
appomatic_django_vcs.egg-info/dependency_links.txt
appomatic_django_vcs.egg-info/requires.txt
appomatic_django_vcs.egg-info/top_level.txt