Metadata-Version: 1.0
Name: appomatic-django-vcs
Version: 0.0.32
Summary: A way to integrate VCS-agnostic repository browsing into Django apps.
Home-page: http://code.google.com/p/django-vcs/
Author: RedHog (Egil Moeller)
Author-email: egil.moller@freecode.no
License: GPL
Keywords: appomatic django-vcs
Platform: UNKNOWN
